patdb/__init__.py
patdb/__main__.py
patdb/_core.py
patdb/_pytest_plugin.py
patdb/py.typed
patdb-0.1.1.dist-info/METADATA
patdb-0.1.1.dist-info/WHEEL
patdb-0.1.1.dist-info/entry_points.txt
patdb-0.1.1.dist-info/licenses/LICENSE
patdb-0.1.1.dist-info/RECORD
