Metadata-Version: 2.4
Name: patdb
Version: 0.1.1
Summary: Pat's Python debugger
Project-URL: repository, https://github.com/patrick-kidger/patdb
Author-email: Patrick Kidger <contact@kidger.site>
License:                                  Apache License
License-File: LICENSE
Keywords: bdb,debug,debugger,patdb,pdb
Classifier: Development Status :: 3 - Alpha
Classifier: License :: OSI Approved :: Apache Software License
Classifier: Natural Language :: English
Classifier: Programming Language :: Python :: 3
Requires-Python: >=3.10
Requires-Dist: click>=8.1.7
Requires-Dist: prompt-toolkit>=3.0.46
Requires-Dist: ptpython>=3.0.27
Requires-Dist: pygments>=2.14.0
Requires-Dist: typing-extensions>=4.5.0
Requires-Dist: wadler-lindig>=0.1.0
